pyadbautomator_package/__init__.py
pyadbautomator_package/pyadbautomator.py
pyadbautomator-0.0.8.dist-info/LICENSE
pyadbautomator-0.0.8.dist-info/METADATA
pyadbautomator-0.0.8.dist-info/WHEEL
pyadbautomator-0.0.8.dist-info/top_level.txt
pyadbautomator-0.0.8.dist-info/RECORD
