Metadata-Version: 2.1
Name: pyadbautomator
Version: 0.0.8
Summary: PyAdbAutomator is a Python library for automating some android tasks using ADB interface
Home-page: https://github.com/guifabrin/pyadbautomator
Author: Guilherme Fabrin Franco
Author-email: guilherme.fabrin@gmail.com
License: UNKNOWN
Project-URL: Bug Tracker, https://github.com/guifabrin/pyadbautomator/issues
Platform: UNKNOWN
Classifier: Programming Language :: Python :: 3
Classifier: License :: OSI Approved :: MIT License
Classifier: Operating System :: OS Independent
Requires-Python: >=3.6
License-File: LICENSE
